deep_lincs/__init__.py
deep_lincs/utils.py
deep_lincs/dataset/__init__.py
deep_lincs/dataset/csv_metadata_loader.py
deep_lincs/dataset/dataset.py
deep_lincs/dataset/gctx_matrix_loader.py
deep_lincs/dataset/load_files.py
deep_lincs/dataset/load_yaml.py
deep_lincs/dataset/normalizers.py
deep_lincs/dataset/tf_dataset_pipeline.py
deep_lincs/enrichr/__init__.py
deep_lincs/enrichr/_enrichr.py
deep_lincs/hidden_embedding/__init__.py
deep_lincs/hidden_embedding/hidden_embedding.py
deep_lincs/models/__init__.py
deep_lincs/models/auto_encoder.py
deep_lincs/models/base_network.py
deep_lincs/models/multi_classifier.py
deep_lincs/models/single_classifier.py
deep_lincs/models/metrics/__init__.py
deep_lincs/models/metrics/pearsons_r.py
deep_lincs/plotting/__init__.py
deep_lincs/plotting/plots.py
deep_lincs-0.0.3.dist-info/LICENSE
deep_lincs-0.0.3.dist-info/METADATA
deep_lincs-0.0.3.dist-info/WHEEL
deep_lincs-0.0.3.dist-info/top_level.txt
deep_lincs-0.0.3.dist-info/RECORD
