Metadata-Version: 2.1
Name: deep-lincs
Version: 0.0.3
Summary: A framework for deep learning with LINCS L1000 Data
Home-page: https://deep-lincs.readthedocs.io
Author: Trevor Manz
Author-email: trevor.j.manz@gmail.com
License: MIT
Download-URL: https://github.com/manzt/deep_lincs
Keywords: LINCS L1000 gene expression
Platform: UNKNOWN
Classifier: Development Status :: 1 - Planning
Classifier: Intended Audience :: Science/Research
Classifier: Programming Language :: Python
